bird/__init__.py
bird/logging_config.py
bird/requirements.txt
bird/version.py
bird/calibration/__init__.py
bird/calibration/param_nn.py
bird/calibration/scaling.py
bird/constants/ch4.yaml
bird/constants/co.yaml
bird/constants/co2.yaml
bird/constants/h2.yaml
bird/constants/h2o.yaml
bird/constants/n2.yaml
bird/constants/o2.yaml
bird/meshing/__init__.py
bird/meshing/_mesh_tools.py
bird/meshing/_stirred_tank_reactor.py
bird/meshing/block_cyl_mesh.py
bird/meshing/block_rect_mesh.py
bird/meshing/stirred_tank_mesh.py
bird/meshing/block_cyl_mesh_templates/baseColumn/input.yaml
bird/meshing/stirred_tank_mesh_templates/base_tank/tank_par.yaml
bird/postprocess/__init__.py
bird/postprocess/conditional_mean.py
bird/postprocess/early_pred.py
bird/postprocess/kla_utils.py
bird/postprocess/post_quantities.py
bird/postprocess/stats.py
bird/postprocess/SA_optimization/get_csv.py
bird/postprocess/SA_optimization/get_optimal.py
bird/postprocess/SA_optimization/get_optimal_with_constraint.py
bird/postprocess/SA_optimization/plot_qoi_vs_sparg.py
bird/postprocess/SA_optimization/surrogate.py
bird/postprocess/computeQoI/compute_QOI.py
bird/preprocess/__init__.py
bird/preprocess/data_case_gen/__init__.py
bird/preprocess/data_case_gen/loop_reactor_pbe_dynmix_nonstat_headbranch_scaleup/get_qoi.py
bird/preprocess/data_case_gen/loop_reactor_pbe_dynmix_nonstat_headbranch_scaleup/read_history.py
bird/preprocess/data_case_gen/loop_reactor_pbe_dynmix_nonstat_headbranch_scaleup/writeGlobalVars.py
bird/preprocess/dynamic_mixer/__init__.py
bird/preprocess/dynamic_mixer/io_fvModels.py
bird/preprocess/dynamic_mixer/mixer.py
bird/preprocess/dynamic_mixer/mixing_fvModels.py
bird/preprocess/inhomogeneousBC/main.py
bird/preprocess/inhomogeneousBC/main_rep.py
bird/preprocess/inhomogeneousBC/util/argument_inhomo.py
bird/preprocess/inhomogeneousBC/util/fromMomtoPdf.py
bird/preprocess/json_gen/__init__.py
bird/preprocess/json_gen/design_io.py
bird/preprocess/json_gen/generate_designs.py
nrel_bird-0.0.50.dist-info/licenses/LICENSE
nrel_bird-0.0.50.dist-info/METADATA
nrel_bird-0.0.50.dist-info/WHEEL
nrel_bird-0.0.50.dist-info/top_level.txt
nrel_bird-0.0.50.dist-info/RECORD
