Metadata-Version: 2.4
Name: nrel-bird
Version: 0.0.50
Summary: Bio Reactor Design (BiRD): a toolbox to simulate and analyze different designs of bioreactors in OpenFOAM
Home-page: https://github.com/NREL/BioReactorDesign
Author: Malik Hassanaly
License: BSD 3-Clause
Project-URL: Documentation, https://nrel.github.io/BioReactorDesign/
Project-URL: Repository, https://github.com/NREL/BioReactorDesign
Classifier: Intended Audience :: Science/Research
Classifier: License :: OSI Approved :: BSD License
Classifier: Natural Language :: English
Classifier: Programming Language :: Python :: 3.10
Classifier: Programming Language :: Python :: 3.13
Requires-Python: >=3.10
License-File: LICENSE
Requires-Dist: numpy
Requires-Dist: prettyPlot
Requires-Dist: ruamel_yaml
Requires-Dist: numpy-stl>=3.2.0
Requires-Dist: scipy
Requires-Dist: corner
Requires-Dist: jax
Requires-Dist: numpyro>=0.16.1
Provides-Extra: calibration
Requires-Dist: joblib; extra == "calibration"
Requires-Dist: tensorflow; extra == "calibration"
Requires-Dist: scikit-learn; extra == "calibration"
Requires-Dist: tf2jax; extra == "calibration"
Provides-Extra: optim
Requires-Dist: optuna; extra == "optim"
Requires-Dist: pandas; extra == "optim"
Dynamic: author
Dynamic: classifier
Dynamic: description
Dynamic: description-content-type
Dynamic: home-page
Dynamic: license
Dynamic: license-file
Dynamic: project-url
Dynamic: provides-extra
Dynamic: requires-dist
Dynamic: requires-python
Dynamic: summary
